{
  "residents_dir": "/tmp/keep_d2_280",
  "since": "2026-06-09T19:27:00+00:00",
  "snapshot_tick": 89,
  "n_speak_acts": 416,
  "channel_mix": {
    "city/broadcast": 258,
    "person": 157,
    "room/Albina": 1
  },
  "keeps_total": 179,
  "keeps_per_resident": {
    "Mateo Ishikawa": 19,
    "Minh Nguyen": 16,
    "Dominic Moretti": 13,
    "Ari Levin": 12,
    "Ari Rosenbaum": 12,
    "Ji-Hoon Park": 12,
    "Jiahao Chen": 12,
    "Amir Mansour": 11,
    "Jihoon Cho": 11,
    "Phuong Tran": 11,
    "Emiko Tanaka": 10,
    "Mateo Villanueva": 9,
    "Ari Goldstein": 8,
    "Darius Washington": 8,
    "Layla Haddad": 8,
    "Layla Al-Khouri": 7
  },
  "top_person_edges": {
    "Ari Rosenbaum->Mateo Villanueva": 9,
    "Jihoon Cho->Mateo Ishikawa": 9,
    "Jiahao Chen->Mateo Ishikawa": 8,
    "Amir Mansour->Mateo Villanueva": 7,
    "Ari Levin->Mateo Villanueva": 7,
    "Ari Levin->Mateo Ishikawa": 6,
    "Darius Washington->Mateo Villanueva": 6,
    "Layla Al-Khouri->Mateo Villanueva": 6,
    "Mateo Ishikawa->Jihoon Cho": 6,
    "Minh Nguyen->Mateo Villanueva": 6,
    "Ari Goldstein->Mateo Villanueva": 5,
    "Layla Haddad->Mateo Villanueva": 5,
    "Amir Mansour->Mateo Ishikawa": 4,
    "Emiko Tanaka->Mateo Villanueva": 4,
    "Ji-Hoon Park->Mateo Villanueva": 4,
    "Ji-Hoon Park->Mateo Ishikawa": 4,
    "Jihoon Cho->Mateo Villanueva": 4,
    "Layla Al-Khouri->Mateo Ishikawa": 4,
    "Layla Haddad->Mateo Ishikawa": 4,
    "Phuong Tran->Mateo Villanueva": 4,
    "Ari Goldstein->Mateo Ishikawa": 3,
    "Dominic Moretti->Mateo Villanueva": 3,
    "Emiko Tanaka->Mateo Ishikawa": 3,
    "Layla Al-Khouri->Jihoon Cho": 3,
    "Phuong Tran->Mateo Ishikawa": 3
  },
  "recipient_in_degree": {
    "Mateo Villanueva": 72,
    "Mateo Ishikawa": 53,
    "Jihoon Cho": 10,
    "Jiahao Chen": 5,
    "Layla Al-Khouri": 5,
    "Ari Goldstein": 3,
    "Layla Haddad": 3,
    "Ari Rosenbaum": 3,
    "Emiko Tanaka": 2,
    "Ari Levin": 1
  }
}